mbvlgranger/__init__.py
mbvlgranger/core.py
mbvlgranger/data_generation.py
mbvlgranger/evaluation.py
mbvlgranger/frequency_analysis.py
mbvlgranger/statistical_tests.py
mbvlgranger/utils.py
mbvlgranger-0.1.2.dist-info/METADATA
mbvlgranger-0.1.2.dist-info/WHEEL
mbvlgranger-0.1.2.dist-info/top_level.txt
mbvlgranger-0.1.2.dist-info/RECORD
