Metadata-Version: 2.4
Name: mbvlgranger
Version: 0.1.2
Summary: Multi-Band Variable-Lag Granger Causality: A Unified Framework for Causal Time Series Inference across Frequencies
Home-page: https://github.com/Teddy50060/MBVLgranger
Author: Chakattrai Sookkongwaree
Author-email: Chakattrai Sookkongwaree <6632033821@student.chula.ac.th>
License: MIT
Project-URL: Homepage, https://github.com/Teddy50060/mbvlgranger
Project-URL: Documentation, https://github.com/Teddy50060/mbvlgranger/docs
Project-URL: Repository, https://github.com/Teddy50060/mbvlgranger.git
Project-URL: Bug Tracker, https://github.com/Teddy50060/mbvlgranger/issues
Keywords: granger-causality,time-series,neuroscience,causality,frequency-analysis
Classifier: Development Status :: 4 - Beta
Classifier: Intended Audience :: Science/Research
Classifier: Topic :: Scientific/Engineering :: Information Analysis
Classifier: License :: OSI Approved :: MIT License
Classifier: Programming Language :: Python :: 3
Classifier: Programming Language :: Python :: 3.8
Classifier: Programming Language :: Python :: 3.9
Classifier: Programming Language :: Python :: 3.10
Classifier: Programming Language :: Python :: 3.11
Requires-Python: >=3.8
Requires-Dist: numpy>=1.20.0
Requires-Dist: pandas>=1.3.0
Requires-Dist: scipy>=1.7.0
Requires-Dist: matplotlib>=3.3.0
Requires-Dist: statsmodels>=0.12.0
Requires-Dist: scikit-learn>=1.0.0
Requires-Dist: dtaidistance>=2.3.0
Provides-Extra: dev
Requires-Dist: pytest>=6.0; extra == "dev"
Requires-Dist: pytest-cov>=2.10; extra == "dev"
Requires-Dist: black>=21.0; extra == "dev"
Requires-Dist: flake8>=3.8; extra == "dev"
Requires-Dist: mypy>=0.812; extra == "dev"
Provides-Extra: docs
Requires-Dist: sphinx>=4.0; extra == "docs"
Requires-Dist: sphinx-rtd-theme>=0.5; extra == "docs"
Provides-Extra: examples
Requires-Dist: jupyter>=1.0; extra == "examples"
Requires-Dist: seaborn>=0.11; extra == "examples"
Dynamic: author
Dynamic: home-page
Dynamic: requires-python
